Workbook

Sheet Global Inputs
B1: GLOBAL ASSUMPTIONS — Change these to update all project calculations
B3: FINANCING
B4: Mortgage Rate (p.a.) — current fixed | C4: 0.015 | D4: Current 3yr fixed rate. Update from bank quotes.
B5: Mortgage Rate (p.a.) — stress test | C5: 0.04 | D5: MAS stress test rate for TDSR calculation.
B6: Mortgage Rate (p.a.) — investment analysis | C6: 0.038 | D6: Rate used for investment carry calculations (expected avg over hold period).
B7: Loan Tenure (years) | C7: 30 | D7: Standard 30yr for private properties.
B8: LTV Ratio — 1st property | C8: 0.75 | D8: 75% max — first residential property.
B9: LTV Ratio — 2nd property | C9: 0.45 | D9: 45% max — second residential property (with outstanding loan).
B11: STAMP DUTIES
B12: ABSD — SC 1st property | C12: 0 | D12: 0% for Singapore Citizen first property.
B13: ABSD — SC 2nd property | C13: 0.2 | D13: 20% for Singapore Citizen second property.
B14: ABSD — SC 3rd+ property | C14: 0.35 | D14: 35% for Singapore Citizen third and subsequent.
B15: ABSD — PR 1st property | C15: 0.05 | D15: 5% for PR first property.
B16: ABSD — PR 2nd+ property | C16: 0.3 | D16: 30% for PR second and subsequent.
B17: ABSD — Foreigner | C17: 0.6 | D17: 60% for foreigners (all properties).
B19: ACQUISITION COSTS
B20: Legal Fees (conveyancing) | C20: 3800 | D20: Typical conveyancing + stamp admin.
B21: Reno & Furnishing (rental-ready) | C21: 20000 | D21: For investment properties. Set 0 for own-stay turnkey.
B22: Agent Commission — Purchase | C22: 0 | D22: Buyer typically pays 0% in SG.
B23: Agent Commission — Sale | C23: 0.01 | D23: 1% of exit price.
B25: RENTAL & TAX ASSUMPTIONS
B26: Occupancy Rate | C26: 0.9 | D26: 90% = ~1 month vacancy per year.
B27: AV as % of Gross Annual Rent | C27: 0.85 | D27: IRAS Annual Value ~85% of market rent.
B28: Effective Property Tax Rate (NROC) | C28: 0.11 | D28: ~11% blended for AV range $40-55K (non-owner-occupied).
B29: Annual Rental Growth Rate | C29: 0.02 | D29: Conservative 2% p.a.
B31: APPRECIATION ASSUMPTIONS (CAGR)
B32: Bear CAGR — Default | C32: 0.02 | D32: Weak market floor. OCR condos ~1-2% historically.
B33: Base CAGR — Default | C33: 0.04 | D33: Moderate growth. Adjust per project.
B34: Bull CAGR — Default | C34: 0.06 | D34: Strong market / catalyst-driven. Adjust per project.
B36: INVESTOR TARGETS
B37: Target Equity IRR | C37: 0.1 | D37: User target: 10%.
B38: Min Holding Period (years) | C38: 4 | D38: SSD clears at 3yrs for private.
B39: Max Holding Period (years) | C39: 6 | D39: Hard outer limit.

Sheet Project Database
B1: PROJECT DATABASE — Singapore Residential Property · Semi-Automated Master
B2: Blue = Inputs (edit per project) | F2: Grey = Auto-calculated from inputs + Global Inputs | L2: Green = Cross-sheet reference
B3: # | C3: Project Name | D3: Priority | E3: District | F3: Area | G3: Type | H3: Bedrooms | I3: Size (sqft) | J3: Budget Min ($) | K3: Budget Max ($) | L3: Avg PSF ($) | M3: Monthly Rent ($) | N3: Tenure | O3: MRT Access | P3: Age / TOP | Q3: Bear CAGR | R3: Base CAGR | S3: Bull CAGR | T3: Gross Yield | U3: Est. Monthly Mortgage | V3: Est. Monthly Carry | W3: Base Exit Price (Yr5) | X3: Bull Exit Price (Yr5) | Y3: Tag / Strategy | Z3: Last Updated
B4: 1 | C4: Rivercove Residences | D4: PRIMARY | E4: D19 | F4: Sengkang | G4: Post-MOP EC | H4: 3BR/2BA | I4: 904-958 | J4: 1350000 | K4: 1430000 | L4: 1615 | M4: 3800 | N4: 99yr | O4: Tongkang LRT → Sengkang NEL | P4: ~6yr (TOP 2020) | Q4: 0.02 | R4: 0.04 | S4: 0.06 | T4: =IF(M4>0,(M4*12)/((J4+K4)/2),"-") -> 0.032805755 | U4: =-PMT('Global Inputs'!C6/12,'Global Inputs'!C7*12,(J4+K4)/2*'Global Inputs'!C8) -> 4857.6054 | V4: =IF(M4>0,M4*'Global Inputs'!C26-U4-380-M4*'Global Inputs'!C27*'Global Inputs'!C28,"-") -> -2172.9054 | W4: =(J4+K4)/2*(1+R4)^5 -> 1691147.5 | X4: =(J4+K4)/2*(1+S4)^5 -> 1860133.6 | Y4: Capital Gain Play | Z4: 2026-04-04
B5: 2 | C5: The Antares | D5: PRIMARY | E5: D14 | F5: Mattar | G5: Private Resale | H5: 2BR/2BA | I5: 657-732 | J5: 1350000 | K5: 1400000 | L5: 2067 | M5: 4200 | N5: 99yr | O5: Mattar DTL (1 min sheltered) | P5: ~4yr (TOP 2022) | Q5: 0.015 | R5: 0.035 | S5: 0.05 | T5: =IF(M5>0,(M5*12)/((J5+K5)/2),"-") -> 0.036654545 | U5: =-PMT('Global Inputs'!C6/12,'Global Inputs'!C7*12,(J5+K5)/2*'Global Inputs'!C8) -> 4805.1852 | V5: =IF(M5>0,M5*'Global Inputs'!C26-U5-380-M5*'Global Inputs'!C27*'Global Inputs'!C28,"-") -> -1797.8852 | W5: =(J5+K5)/2*(1+R5)^5 -> 1633068.7 | X5: =(J5+K5)/2*(1+S5)^5 -> 1754887.1 | Y5: Yield & Carry Minimiser | Z5: 2026-04-04
B6: 3 | C6: ECO at Bedok | D6: SECONDARY | E6: D16 | F6: Bedok South | G6: Private Resale | H6: 2BR/2BA | I6: 700-850 | J6: 1080000 | K6: 1340000 | L6: 1549 | M6: 3900 | N6: 99yr | O6: Tanah Merah EWL + Bedok South TEL | P6: ~13yr (TOP 2013) | Q6: 0.02 | R6: 0.038 | S6: 0.05 | T6: =IF(M6>0,(M6*12)/((J6+K6)/2),"-") -> 0.038677686 | U6: =-PMT('Global Inputs'!C6/12,'Global Inputs'!C7*12,(J6+K6)/2*'Global Inputs'!C8) -> 4228.563 | V6: =IF(M6>0,M6*'Global Inputs'!C26-U6-380-M6*'Global Inputs'!C27*'Global Inputs'!C28,"-") -> -1463.213 | W6: =(J6+K6)/2*(1+R6)^5 -> 1458049.1 | X6: =(J6+K6)/2*(1+S6)^5 -> 1544300.7 | Y6: Yield + TEL Catalyst | Z6: 2026-04-04
B7: 4 | C7: Treasure at Tampines | D7: SECONDARY | E7: D18 | F7: Tampines | G7: Private Resale | H7: 2BR/2BA | I7: ~700 | J7: 1190000 | K7: 1270000 | L7: 1700 | M7: 3600 | N7: 99yr | O7: Tampines EWL/DTL (10 min walk) | P7: ~3yr (TOP 2023) | Q7: 0.015 | R7: 0.035 | S7: 0.045 | T7: =IF(M7>0,(M7*12)/((J7+K7)/2),"-") -> 0.035121951 | U7: =-PMT('Global Inputs'!C6/12,'Global Inputs'!C7*12,(J7+K7)/2*'Global Inputs'!C8) -> 4298.4566 | V7: =IF(M7>0,M7*'Global Inputs'!C26-U7-380-M7*'Global Inputs'!C27*'Global Inputs'!C28,"-") -> -1775.0566 | W7: =(J7+K7)/2*(1+R7)^5 -> 1460854.2 | X7: =(J7+K7)/2*(1+S7)^5 -> 1532803.8 | Y7: Liquidity & Mainstream | Z7: 2026-04-04
B8: 5 | C8: The Florence Residences | D8: SECONDARY | E8: D19 | F8: Hougang/Kovan | G8: Private Resale | H8: 2BR/2BA | I8: ~700 | J8: 1200000 | K8: 1400000 | L8: 1800 | M8: 3500 | N8: 99yr | O8: Hougang NEL (walking distance) | P8: ~4yr (TOP 2022) | Q8: 0.015 | R8: 0.035 | S8: 0.05 | T8: =IF(M8>0,(M8*12)/((J8+K8)/2),"-") -> 0.032307692 | U8: =-PMT('Global Inputs'!C6/12,'Global Inputs'!C7*12,(J8+K8)/2*'Global Inputs'!C8) -> 4543.0842 | V8: =IF(M8>0,M8*'Global Inputs'!C26-U8-380-M8*'Global Inputs'!C27*'Global Inputs'!C28,"-") -> -2100.3342 | W8: =(J8+K8)/2*(1+R8)^5 -> 1543992.2 | X8: =(J8+K8)/2*(1+S8)^5 -> 1659166 | Y8: D19 Private Alternative | Z8: 2026-04-04
B9: 6 | C9: Wandervale EC | D9: MONITOR | E9: D23 | F9: Choa Chu Kang | G9: Post-MOP EC | H9: 3BR/2BA | I9: 950-1100 | J9: 1250000 | K9: 1400000 | L9: 1375 | M9: 3500 | N9: 99yr | O9: Choa Chu Kang NSL (10 min walk) | P9: ~7yr (MOP 2023) | Q9: 0.015 | R9: 0.03 | S9: 0.04 | T9: =IF(M9>0,(M9*12)/((J9+K9)/2),"-") -> 0.031698113 | U9: =-PMT('Global Inputs'!C6/12,'Global Inputs'!C7*12,(J9+K9)/2*'Global Inputs'!C8) -> 4630.4512 | V9: =IF(M9>0,M9*'Global Inputs'!C26-U9-380-M9*'Global Inputs'!C27*'Global Inputs'!C28,"-") -> -2187.7012 | W9: =(J9+K9)/2*(1+R9)^5 -> 1536038.1 | X9: =(J9+K9)/2*(1+S9)^5 -> 1612065.1 | Y9: Value EC / JLD Optionality | Z9: 2026-04-04
B10: 7 | C10: Twin Fountains / Bellewoods | D10: MONITOR | E10: D25 | F10: Woodlands | G10: Post-MOP EC | H10: 3BR/2BA | I10: 1100-1250 | J10: 1200000 | K10: 1450000 | L10: 1325 | M10: 3800 | N10: 99yr | O10: Admiralty NSL + Woodlands South TEL | P10: ~9yr (TOP 2016/17) | Q10: 0.015 | R10: 0.03 | S10: 0.045 | T10: =IF(M10>0,(M10*12)/((J10+K10)/2),"-") -> 0.034415094 | U10: =-PMT('Global Inputs'!C6/12,'Global Inputs'!C7*12,(J10+K10)/2*'Global Inputs'!C8) -> 4630.4512 | V10: =IF(M10>0,M10*'Global Inputs'!C26-U10-380-M10*'Global Inputs'!C27*'Global Inputs'!C28,"-") -> -1945.7512 | W10: =(J10+K10)/2*(1+R10)^5 -> 1536038.1 | X10: =(J10+K10)/2*(1+S10)^5 -> 1651191.1 | Y10: Yield + Privatisation | Z10: 2026-04-04
B11: 8 | C11: Piermont Grand | D11: MONITOR | E11: D19 | F11: Punggol | G11: Post-MOP EC | H11: 3BR/2BA | I11: 840+ | J11: 1430000 | K11: 1500000 | L11: 1735 | M11: 3600 | N11: 99yr | O11: Sumang LRT → Punggol NEL | P11: ~3yr (TOP 2023) | Q11: 0.02 | R11: 0.04 | S11: 0.06 | T11: =IF(M11>0,(M11*12)/((J11+K11)/2),"-") -> 0.029488055 | U11: =-PMT('Global Inputs'!C6/12,'Global Inputs'!C7*12,(J11+K11)/2*'Global Inputs'!C8) -> 5119.7064 | V11: =IF(M11>0,M11*'Global Inputs'!C26-U11-380-M11*'Global Inputs'!C27*'Global Inputs'!C28,"-") -> -2596.3064 | W11: =(J11+K11)/2*(1+R11)^5 -> 1782396.5 | X11: =(J11+K11)/2*(1+S11)^5 -> 1960500.5 | Y11: PDD Play (Budget Stretch) | Z11: 2026-04-04
B12: 9 | C12: Rivelle Tampines EC | D12: CONDITIONAL | E12: D18 | F12: Tampines West | G12: New EC Launch | H12: 2BR/3BR | I12: TBD | J12: 1300000 | K12: 1580000 | L12: 1796 | M12: 0 | N12: 99yr | O12: Tampines West DTL (direct) | P12: New (TOP ~2029) | Q12: 0.03 | R12: 0.045 | S12: 0.06 | T12: =IF(M12>0,(M12*12)/((J12+K12)/2),"-") -> - | U12: =-PMT('Global Inputs'!C6/12,'Global Inputs'!C7*12,(J12+K12)/2*'Global Inputs'!C8) -> 5032.3394 | V12: =IF(M12>0,M12*'Global Inputs'!C26-U12-380-M12*'Global Inputs'!C27*'Global Inputs'!C28,"-") -> - | W12: =(J12+K12)/2*(1+R12)^5 -> 1794502 | X12: =(J12+K12)/2*(1+S12)^5 -> 1927044.8 | Y12: EC First-Mover | Z12: 2026-04-04
B13: 10 | C13: The Botany at Dairy Farm | D13: SPECULATIVE | E13: D23 | F13: Dairy Farm | G13: Near-TOP Subsale | H13: 2BR/2BA | I13: 650-750 | J13: 1200000 | K13: 1380000 | L13: 1950 | M13: 3000 | N13: 99yr | O13: Hillview DTL (walk) | P13: New (TOP 2027) | Q13: 0.01 | R13: 0.025 | S13: 0.04 | T13: =IF(M13>0,(M13*12)/((J13+K13)/2),"-") -> 0.027906977 | U13: =-PMT('Global Inputs'!C6/12,'Global Inputs'!C7*12,(J13+K13)/2*'Global Inputs'!C8) -> 4508.1374 | V13: =IF(M13>0,M13*'Global Inputs'!C26-U13-380-M13*'Global Inputs'!C27*'Global Inputs'!C28,"-") -> -2468.6374 | W13: =(J13+K13)/2*(1+R13)^5 -> 1459516.6 | X13: =(J13+K13)/2*(1+S13)^5 -> 1569482.2 | Y13: Lifestyle / Speculative | Z13: 2026-04-04

Sheet Project Notes
B1: PROJECT NOTES — Investment Thesis · Catalysts · Risks · Target Unit Spec
A3: # | B3: Project | C3: Investment Thesis | D3: Key Catalysts | E3: Key Risks | F3: Target Unit Specification
A4: 1 | B4: Rivercove Residences D19 · Post-MOP EC [PRIMARY] | C4: Freshly MOP'd Oct 2025. EC-to-private price gap fully intact. Waterfront on Punggol Reservoir. Hundred Palms trajectory is the template. | D4: EC price discovery phase Waterfront reservoir facing PDD adjacency School cluster | E4: LRT dependency (not direct MRT) D19 supply pipeline 3.0% yield = higher carry | F4: Mid-floor 5F-10F, reservoir/greenery facing, 3BR Type A 904 sqft. Max $1,580 psf.
A5: 2 | B5: The Antares D14 · Private Resale [PRIMARY] | C5: Highest yield on shortlist. Sheltered 1-min walk to Mattar MRT DTL. Paya Lebar, Bidadari, Geylang rezoning — three macro catalysts converge. | D5: Mattar MRT DTL direct Paya Lebar Regional Centre Bidadari transformation Geylang rezoning | E5: Small unit 657 sqft Story partially priced at $2,067 psf Limited capital gain vs EC plays | F5: 657 sqft 2BR mid-high floor, quiet-facing. ~$1.35-1.38M. Best carry minimiser.
A6: 3 | B6: ECO at Bedok D16 · Private Resale [SECONDARY] | C6: Most material finding. TEL Bedok South confirmed 2026 — dual-line access. D16 PSF rose 44.4% (2020-2025). Best yield-per-dollar with budget headroom. | D6: TEL Bedok South opening 2026 Dual-line MRT access Mature estate Large HDB upgrader pool | E6: 13yr old at purchase — 17-19yr at exit Buyer financing may tighten Lower capital gain ceiling | F6: 2BR 667-850 sqft, mid-floor, park/greenery facing. Buy below $1,550 psf.
A7: 4 | B7: Treasure at Tampines D18 · Private Resale [SECONDARY] | C7: Deepest resale liquidity — 170 units transacted 2025. Changi Business Park tenant base. Newer stock, broad buyer pool. | D7: Highest transaction liquidity Changi Biz Park demand Tampines Regional Hub Newer 2023 product | E7: 2,200 units = heavy internal competition 10-min walk to MRT Yield below best-in-class | F7: 2BR mid-floor, pool/greenery facing (not carpark). Stack and facing critical.
A8: 5 | B8: The Florence Residences D19 · Private Resale [SECONDARY] | C8: Newer private in D19 with Hougang MRT NEL direct. Same district demand as Rivercove without EC price discovery upside. | D8: D19 demand fundamentals Hougang MRT NEL direct Newer 2022 product CRL future benefit | E8: 1,410 units = significant competition No EC price gap catalyst Lower yield | F8: 2BR mid-floor, well-facing stack. Avoid ground floor and carpark. Budget $1.20-1.38M.
A9: 6 | B9: Wandervale EC D23 · Post-MOP EC [MONITOR] | C9: Lower-profile post-MOP EC with NSL connectivity to JLD. Less competitive buying = more negotiation room. | D9: NSL → JLD employment hub EC value gap to private Negotiable entry Family 3BR | E9: JLD is 10yr story not 4-6yr Weaker rental submarket Limited professional tenant pool | F9: 3BR 950+ sqft, mid-floor, greenery facing. Target below $1,380 psf.
A10: 7 | B10: Twin Fountains / Bellewoods D25 · Post-MOP EC [MONITOR] | C10: Highest yield (~3.5-4.0%). Twin Fountains privatises 2026. RTS Link targeted end-2026. New EC launches at $1,750-2,000 psf create $400-700 gap. | D10: Privatisation 2026 RTS Link end-2026 New EC benchmarks $1,800+ psf Woodlands transformation | E10: Suppressed private ceiling in D25 Thin exit buyer pool 9yr aging stock RTS timing risk | F10: 3BR 1,100+ sqft, mid-floor, non-carpark. Buy below $1,300 psf. Best: motivated post-privatisation seller.
A11: 8 | B11: Piermont Grand D19 · Post-MOP EC [MONITOR] | C11: Best physical product in Punggol — waterway-fronting, PDD adjacent, CDL. First PDD hotel confirmed 2026-27. Borderline above budget. | D11: PDD first hotel 2026-2027 Waterway-fronting premium SIT campus tenant base CDL developer quality | E11: Above $1.4M budget at market LRT dependency Large Punggol supply 3BR+ only = narrow pool | F11: 3BR 840 sqft, waterway/reservoir facing, mid-floor. Buy only at/below $1,700 psf (~$1.43M).
A12: 9 | B12: Rivelle Tampines EC D18 · New EC Launch [CONDITIONAL] | C12: First-mover EC play — buy at launch, hold through MOP, exit as privatised condo. Same thesis as Hundred Palms. Requires strict EC eligibility. | D12: EC-to-private gap at launch CRL Tampines North Tampines West emerging First large dev in area | E12: 5yr MOP lock-in EC eligibility rules — verify TOP 2029-2030 Budget tight for 3BR | F12: Only if EC eligible. 2BR for budget control. Do not purchase without verifying all conditions.
A13: 10 | B13: The Botany at Dairy Farm D23 · Near-TOP Subsale [SPECULATIVE] | C13: Near-TOP subsale near nature. Dairy Farm is differentiated. Investment thesis weak; lifestyle thesis strong. Only if priced right. | D13: New product at subsale discount Nature/greenery differentiation Hillview DTL Near-TOP — no wait | E13: Narrow tenant pool D23 supply glut incoming Limited resale liquidity Speculative pricing | F13: Only if subsale below $1,800 psf. Not core investment — lifestyle play.

Sheet BSD Calculator
B1: BSD CALCULATOR — Enter purchase price, get BSD
B3: Purchase Price (S$) | C3: 1380000
B5: Bracket | C5: BSD Amount
B6: First $180,000 @ 1% | C6: =MIN(C3,180000)*0.01 -> 1800
B7: Next $180,000 @ 2% | C7: =MIN(MAX(C3-180000,0),180000)*0.02 -> 3600
B8: Next $640,000 @ 3% | C8: =MIN(MAX(C3-360000,0),640000)*0.03 -> 19200
B9: Next $500,000 @ 4% | C9: =MIN(MAX(C3-1000000,0),500000)*0.04 -> 15200
B10: Next $1,500,000 @ 5% | C10: =MIN(MAX(C3-1500000,0),1500000)*0.05 -> 0
B11: Above $3,000,000 @ 6% | C11: =MAX(C3-3000000,0)*0.06 -> 0
B13: TOTAL BSD | C13: =SUM(C6:C11) -> 39800
